MANIFEST.in
README.rst
setup.cfg
setup.py
botkit/__init__.py
botkit.egg-info/PKG-INFO
botkit.egg-info/SOURCES.txt
botkit.egg-info/dependency_links.txt
botkit.egg-info/top_level.txt