Metadata-Version: 1.1
Name: botkit
Version: 0.1
Summary: A python toolkit to write intelligent bots.
Home-page: https://github.com/srikris/botkit
Author: The Python Packaging Authority
Author-email: srikrishna097@gmail.com
License: BSD
Keywords: bot machine learning artificial intelligence
Platform: UNKNOWN
Classifier: Development Status :: 3 - Alpha
Classifier: Intended Audience :: Developers
Classifier: Topic :: Software Development :: Build Tools
Classifier: License :: OSI Approved :: BSD License
Classifier: Programming Language :: Python :: 2
Classifier: Programming Language :: Python :: 2.6
Classifier: Programming Language :: Python :: 2.7
Classifier: Programming Language :: Python :: 3
Classifier: Programming Language :: Python :: 3.2
Classifier: Programming Language :: Python :: 3.3
Classifier: Programming Language :: Python :: 3.4
Classifier: Programming Language :: Python :: 3.5
